{
  "main": {
    "id": "6c407dad3f953551",
    "type": "split",
    "children": [
      {
        "id": "0e46b715a8fb5290",
        "type": "tabs",
        "children": [
          {
            "id": "e16d164d1c8d4d69",
            "type": "leaf",
            "state": {
              "type": "markdown",
              "state": {
                "file": "possible help for diss.md",
                "mode": "source",
                "source": false
              },
              "icon": "lucide-file",
              "title": "possible help for diss"
            }
          }
        ]
      }
    ],
    "direction": "vertical"
  },
  "left": {
    "id": "c706cca3de1abec9",
    "type": "split",
    "children": [
      {
        "id": "3ed967d4294081af",
        "type": "tabs",
        "children": [
          {
            "id": "e5bf19fa09400529",
            "type": "leaf",
            "state": {
              "type": "file-explorer",
              "state": {
                "sortOrder": "byModifiedTime",
                "autoReveal": false
              },
              "icon": "lucide-folder-closed",
              "title": "Files"
            }
          },
          {
            "id": "4128250eba8ba64e",
            "type": "leaf",
            "state": {
              "type": "search",
              "state": {
                "query": "",
                "matchingCase": false,
                "explainSearch": false,
                "collapseAll": false,
                "extraContext": false,
                "sortOrder": "alphabetical"
              },
              "icon": "lucide-search",
              "title": "Search"
            }
          },
          {
            "id": "04dea3e0f937eadb",
            "type": "leaf",
            "state": {
              "type": "bookmarks",
              "state": {},
              "icon": "lucide-bookmark",
              "title": "Bookmarks"
            }
          }
        ]
      }
    ],
    "direction": "horizontal",
    "width": 239.5110321044922,
    "collapsed": true
  },
  "right": {
    "id": "09ff80183222ed7a",
    "type": "split",
    "children": [
      {
        "id": "aa6a0501cd9a881a",
        "type": "tabs",
        "children": [
          {
            "id": "78e99932896249fd",
            "type": "leaf",
            "state": {
              "type": "backlink",
              "state": {
                "file": "Crime and Punishment/Prisons.md",
                "collapseAll": false,
                "extraContext": false,
                "sortOrder": "alphabetical",
                "showSearch": false,
                "searchQuery": "",
                "backlinkCollapsed": false,
                "unlinkedCollapsed": true
              },
              "icon": "links-coming-in",
              "title": "Backlinks for Prisons"
            }
          },
          {
            "id": "19ae7a1e8ec2c90c",
            "type": "leaf",
            "state": {
              "type": "outgoing-link",
              "state": {
                "file": "Crime and Punishment/Prisons.md",
                "linksCollapsed": false,
                "unlinkedCollapsed": true
              },
              "icon": "links-going-out",
              "title": "Outgoing links from Prisons"
            }
          },
          {
            "id": "3837a677296408a4",
            "type": "leaf",
            "state": {
              "type": "tag",
              "state": {
                "sortOrder": "frequency",
                "useHierarchy": true
              },
              "icon": "lucide-tags",
              "title": "Tags"
            }
          },
          {
            "id": "9ec458c107a2e094",
            "type": "leaf",
            "state": {
              "type": "outline",
              "state": {
                "file": "Crime and Punishment/Prisons.md",
                "followCursor": false,
                "showSearch": false,
                "searchQuery": ""
              },
              "icon": "lucide-list",
              "title": "Outline of Prisons"
            }
          }
        ]
      }
    ],
    "direction": "horizontal",
    "width": 300,
    "collapsed": true
  },
  "left-ribbon": {
    "hiddenItems": {
      "obsidian-git:Open Git source control": false,
      "switcher:Open quick switcher": false,
      "graph:Open graph view": false,
      "canvas:Create new canvas": false,
      "daily-notes:Open today's daily note": false,
      "templates:Insert template": false,
      "command-palette:Open command palette": false
    }
  },
  "active": "e16d164d1c8d4d69",
  "lastOpenFiles": [
    "Dissertation proposal.md",
    "possible help for diss.md",
    "used notes/How Bloody was the Bloody Code.md",
    "home",
    "/home/cole/Documents/obsidian-notes/Second Semester/usr/share/fonts/TTF/JetBrainsMonoNLNerdFontMono-Medium.ttf/",
    "/home/cole/Documents/obsidian-notes/Second Semester/usr/share/fonts/TTF/JetBrainsMonoNLNerdFontMono-Medium.ttf",
    "/home/cole/Documents/obsidian-notes/Second Semester/usr/share/fonts/TTF",
    "/home/cole/Documents/obsidian-notes/Second Semester/usr/share/fonts",
    "/home/cole/Documents/obsidian-notes/Second Semester/usr/share",
    "/home/cole/Documents/obsidian-notes/Second Semester/usr",
    "/home/cole/Documents/obsidian-notes/Second Semester",
    "/home/cole/Documents/obsidian-notes",
    "/home/cole/Documents",
    "Crime and Punishment/Punishment.md",
    "Crime and Punishment/The life of a pirate.md",
    "Crime and Punishment/Reading the first.md",
    "Crime and Punishment/women and crime.md",
    "Crime and Punishment/from parish constables to detectives.md",
    "used notes/Valentines day planning.md",
    "used notes/Blog Posts reading pop cult.md",
    "used notes/Blog Post Knights of the Air.md",
    "images/Pasted image 20250211133544.png",
    "images/Pasted image 20250208140358.png",
    "images/Pasted image 20250218144124.png",
    "images/Pasted image 20250218144152.png",
    "images/Pasted image 20250508140310.jpg",
    "Untitled 1.md",
    "images/Pasted image 20250508140334.jpg",
    "images/Pasted image 20250508140317.jpg",
    "images/Pasted image 20250508140230.jpg",
    "images/xwsaztdaoosmspmprf9blv2le_-ktzjn-99ba.webp",
    "used notes/Medieval presentation.md",
    "test file.md",
    "any type.md",
    "Medieval Chivalry/reading for medieval.md",
    "Crime and Punishment/Juvenile delinquents.md",
    "Crime and Punishment/From Magistrates to Jurors.md",
    "used notes/Crime Act Pres.md",
    "Medieval Chivalry/Rachel and medieval tabletop games.md",
    "Crime and Punishment/Prisons.md",
    "obsidian-notes/README.md",
    "Dissertation Research Skills/Dissertation research skills blog thing.md",
    "Medieval Chivalry/books and shit to remember for medieval.md",
    "Medieval Chivalry/Medievalism.md",
    "Medieval Chivalry/Chivalry and War.md",
    "images/Pasted image 20250218143734.png",
    "Untitled.canvas"
  ]
}